keap/Keap.py
keap/KeapToken.py
keap/__init__.py
keap/exceptions.py
keap/module_loading.py
keap/settings.py
keap/REST/BaseService.py
keap/REST/REST_V1.py
keap/REST/__init__.py
keap/REST/models.py
keap/REST/V1/AccountService.py
keap/REST/V1/AffiliateService.py
keap/REST/V1/AppointmentService.py
keap/REST/V1/CampaignService.py
keap/REST/V1/CompanyService.py
keap/REST/V1/ContactService.py
keap/REST/V1/EmailService.py
keap/REST/V1/FileService.py
keap/REST/V1/HookService.py
keap/REST/V1/LocaleService.py
keap/REST/V1/MerchantService.py
keap/REST/V1/NoteService.py
keap/REST/V1/OpportunityService.py
keap/REST/V1/OrderService.py
keap/REST/V1/ProductService.py
keap/REST/V1/SettingService.py
keap/REST/V1/SubscriptionService.py
keap/REST/V1/TagService.py
keap/REST/V1/TaskService.py
keap/REST/V1/TransactionService.py
keap/REST/V1/UserService.py
keap/REST/V1/__init__.py
keap/REST/V1/mixins.py
keap/XML/AffiliateProgramService.py
keap/XML/AffiliateService.py
keap/XML/BaseService.py
keap/XML/ContactService.py
keap/XML/DataService.py
keap/XML/DiscountService.py
keap/XML/EmailService.py
keap/XML/FileService.py
keap/XML/FunnelService.py
keap/XML/InvoiceService.py
keap/XML/OrderService.py
keap/XML/ProductService.py
keap/XML/SearchService.py
keap/XML/ShippingService.py
keap/XML/WebFormService.py
keap/XML/XML.py
keap/XML/__init__.py
keap/scripts/__init__.py
keap/scripts/cli.py
keap/storages/BaseStorage.py
keap/storages/InMemoryStorage.py
keap/storages/JSONStorage.py
keap/storages/__init__.py
keap_python-1.3.0.dist-info/METADATA
keap_python-1.3.0.dist-info/WHEEL
keap_python-1.3.0.dist-info/entry_points.txt
keap_python-1.3.0.dist-info/top_level.txt
keap_python-1.3.0.dist-info/RECORD
